airflow_spark_k8s/__init__.py
airflow_spark_k8s/hooks/__init__.py
airflow_spark_k8s/hooks/kubernetes.py
airflow_spark_k8s/operators/__init__.py
airflow_spark_k8s/operators/spark_kubernetes.py
airflow_spark_k8s/sensors/__init__.py
airflow_spark_k8s/sensors/spark_kubernetes.py
airflow_spark_k8s-0.1.4.dist-info/METADATA
airflow_spark_k8s-0.1.4.dist-info/WHEEL
airflow_spark_k8s-0.1.4.dist-info/top_level.txt
airflow_spark_k8s-0.1.4.dist-info/RECORD
